{  
   "datas":[  
      {  
         "year":"2018",
         "months":[  
            {  
               "month":"janvier",
               "income":"1505.09",
               "outcome":"2822.58",
               "inbank":"6300",
               "categories":[  
                  {  
                     "name":"nourriture",
                     "value":"1000"
                  },
                  {  
                     "name":"resto",
                     "value":"505.09"
                  }
               ]
            },
            {  
               "month":"février",
               "income":"1622.39",
               "outcome":"1156.16",
               "inbank":"6800",
               "categories":[  
                  {  
                     "name":"nourriture",
                     "value":"1000"
                  },
                  {  
                     "name":"resto",
                     "value":"156.16"
                  }
               ]
            },
            {  
               "month":"mars",
               "income":"1789.13",
               "outcome":"1163.34",
               "inbank":"7300",
               "categories":[  
                  {  
                     "name":"nourriture",
                     "value":"1000"
                  },
                  {  
                     "name":"resto",
                     "value":"163.34"
                  }
               ]
            },
            {  
               "month":"avril",
               "income":"1705.10",
               "outcome":"1317.44",
               "inbank":"7900",
               "categories":[  
                  {  
                     "name":"nourriture",
                     "value":"1000"
                  },
                  {  
                     "name":"resto",
                     "value":"317.44"
                  }
               ]
            },
            {  
               "month":"mai",
               "income":"1656.83",
               "outcome":"1300.52",
               "inbank":"8300",
               "categories":[  
                  {  
                     "name":"nourriture",
                     "value":"1000"
                  },
                  {  
                     "name":"resto",
                     "value":"300.52"
                  }
               ]
            },
            {  
               "month":"juin",
               "income":"2009.51",
               "outcome":"1608",
               "inbank":"8700",
               "categories":[  
                  {  
                     "name":"nourriture",
                     "value":"1000"
                  },
                  {  
                     "name":"resto",
                     "value":"608"
                  }
               ]
            },
            {  
               "month":"juillet",
               "income":"2254.91",
               "outcome":"1393.86",
               "inbank":"9600",
               "categories":[  
                  {  
                     "name":"nourriture",
                     "value":"1000"
                  },
                  {  
                     "name":"resto",
                     "value":"393.86"
                  }
               ]
            }
         ],
         "current":{  
            "currentMonth":"aout",
            "expenses":[  
               {  
                  "name":"course",
                  "category":"nourriture",
                  "date":"07/08/2018",
                  "type":"outcome",
                  "value":"94.95"
               },
               {  
                  "name":"tuto Udemy",
                  "category":"tuto",
                  "date":"01/08/2018",
                  "type":"outcome",
                  "value":"9.99"
               },
               {  
                  "name":"tuto Udemy",
                  "category":"tuto",
                  "date":"23/08/2018",
                  "type":"outcome",
                  "value":"9.99 "
               },
               {  
                  "name":"essence",
                  "category":"voiture",
                  "date":"14/08/2018",
                  "type":"outcome",
                  "value":"25.01"
               },
               {  
                  "name":"paie",
                  "category":"salaire",
                  "date":"17/08/2018",
                  "type":"income",
                  "value":"1513.56"
               },
               {  
                  "name":"coiffeur",
                  "category":"coiffeur",
                  "date":"08/08/2018",
                  "type":"outcome",
                  "value":"20.00"
               },
               {  
                  "name":"jeux",
                  "category":"jeux",
                  "date":"24/08/2018",
                  "type":"outcome",
                  "value":"15.86"
               }
            ]
         }
      },
      {  
         "year":"2017",
         "months":[  
            {  
               "month":"janvier",
               "income":"1502.37",
               "outcome":"1426.71",
               "inbank":"5600",
               "categories":[  
                  {  
                     "name":"nourriture",
                     "value":"1000"
                  },
                  {  
                     "name":"resto",
                     "value":"426.71"
                  }
               ]
            },
            {  
               "month":"février",
               "income":"1518.59",
               "outcome":"3607.75",
               "inbank":"3300",
               "categories":[  
                  {  
                     "name":"nourriture",
                     "value":"1000"
                  },
                  {  
                     "name":"voyage",
                     "value":"2000"
                  },
                  {  
                     "name":"jardin",
                     "value":"607.75"
                  }
               ]
            },
            {  
               "month":"mars",
               "income":"1431.99",
               "outcome":"1673.48",
               "inbank":"3300",
               "categories":[  
                  {  
                     "name":"nourriture",
                     "value":"1000"
                  },
                  {  
                     "name":"jardin",
                     "value":"673.48"
                  }
               ]
            },
            {  
               "month":"avril",
               "income":"2111.89",
               "outcome":"1344.73",
               "inbank":"3800",
               "categories":[  
                  {  
                     "name":"nourriture",
                     "value":"1000"
                  },
                  {  
                     "name":"jardin",
                     "value":"344.73"
                  }
               ]
            },
            {  
               "month":"mai",
               "income":"1861.85",
               "outcome":"1027.77",
               "inbank":"4600",
               "categories":[  
                  {  
                     "name":"nourriture",
                     "value":"1000"
                  },
                  {  
                     "name":"jardin",
                     "value":"27.77"
                  }
               ]
            },
            {  
               "month":"juin",
               "income":"3720.76",
               "outcome":"3041.32",
               "inbank":"5000",
               "categories":[  
                  {  
                     "name":"nourriture",
                     "value":"1000"
                  },
                  {  
                     "name":"voyage",
                     "value":"2000"
                  },
                  {  
                     "name":"jardin",
                     "value":"41.32"
                  }
               ]
            },
            {  
               "month":"juillet",
               "income":"2131.99",
               "outcome":"1846.29",
               "inbank":"5600",
               "categories":[  
                  {  
                     "name":"nourriture",
                     "value":"1000"
                  },
                  {  
                     "name":"voyage",
                     "value":"800"
                  },
                  {  
                     "name":"jardin",
                     "value":"46.29"
                  }
               ]
            },
            {  
               "month":"aout",
               "income":"1491.99",
               "outcome":"1646.35",
               "inbank":"5600",
               "categories":[  
                  {  
                     "name":"nourriture",
                     "value":"1000"
                  },
                  {  
                     "name":"voyage",
                     "value":"600"
                  },
                  {  
                     "name":"jardin",
                     "value":"46.35"
                  }
               ]
            },
            {  
               "month":"septembre",
               "income":"1531.11",
               "outcome":"1214.56",
               "inbank":"5800",
               "categories":[  
                  {  
                     "name":"nourriture",
                     "value":"1000"
                  },
                  {  
                     "name":"voyage",
                     "value":"14.56"
                  },
                  {  
                     "name":"jardin",
                     "value":"200"
                  }
               ]
            },
            {  
               "month":"octobre",
               "income":"1473.39",
               "outcome":"1151.69",
               "inbank":"6400",
               "categories":[  
                  {  
                     "name":"nourriture",
                     "value":"1000"
                  },
                  {  
                     "name":"voyage",
                     "value":"100"
                  },
                  {  
                     "name":"jardin",
                     "value":"51.69"
                  }
               ]
            },
            {  
               "month":"novembre",
               "income":"451.19",
               "outcome":"1577.49",
               "inbank":"5100",
               "categories":[  
                  {  
                     "name":"nourriture",
                     "value":"1000"
                  },
                  {  
                     "name":"voyage",
                     "value":"77.49"
                  },
                  {  
                     "name":"jardin",
                     "value":"500"
                  }
               ]
            },
            {  
               "month":"décembre",
               "income":"3916.29",
               "outcome":"1633.04",
               "inbank":"7500",
               "categories":[  
                  {  
                     "name":"nourriture",
                     "value":"1000"
                  },
                  {  
                     "name":"voyage",
                     "value":"33.04"
                  },
                  {  
                     "name":"jardin",
                     "value":"600"
                  }
               ]
            }
         ]
      }
   ],
   "dataTemp":{  
      "currentYear":"2018",
      "currentMonth":"aout"
   },
   "searches":{  
      "categories":[  
         "jeux",
         "nourriture"
      ],
      "names":[  
         "coiffuer",
         "course",
         "tuto"
      ]
   }
}